squadbase/streamlit/__init__.py
squadbase/streamlit/auth/__init__.py
squadbase/streamlit/auth/user.py
squadbase_streamlit-0.0.1.dist-info/METADATA
squadbase_streamlit-0.0.1.dist-info/WHEEL
squadbase_streamlit-0.0.1.dist-info/RECORD
