Metadata-Version: 2.1
Name: squadbase-streamlit
Version: 0.0.1
Summary: Squadbase Python SDK for Streamlit
Home-page: https://www.squadbase.dev
License: Apache-2.0
Author: squadbase
Author-email: contact@morphdb.io
Requires-Python: >=3.9, !=2.7.*, !=3.0.*, !=3.1.*, !=3.2.*, !=3.3.*, !=3.4.*, !=3.5.*, !=3.6.*, !=3.7.*, !=3.8.*
Classifier: Development Status :: 3 - Alpha
Classifier: Environment :: Web Environment
Classifier: Intended Audience :: Developers
Classifier: Intended Audience :: Science/Research
Classifier: License :: OSI Approved :: Apache Software License
Classifier: Programming Language :: Python :: 3
Classifier: Programming Language :: Python :: 3.9
Classifier: Programming Language :: Python :: 3.10
Classifier: Programming Language :: Python :: 3.11
Classifier: Programming Language :: Python :: 3.12
Classifier: Programming Language :: Python :: 3.13
Classifier: Topic :: Software Development :: Libraries
Classifier: Topic :: Software Development :: Libraries :: Python Modules
Classifier: Topic :: Software Development :: User Interfaces
Requires-Dist: requests (>=2.31.0,<3.0.0)
Requires-Dist: streamlit (>=1.44.1,<2.0.0)
Project-URL: Repository, https://github.com/squadbase/squadbase-streamlit
